README.md
mvodb/__init__.py
mvodb/__main__.py
mvodb/cli.py
pyproject.toml
mvodb-0.1.0.dist-info/entry_points.txt
mvodb-0.1.0.dist-info/LICENSE
mvodb-0.1.0.dist-info/WHEEL
mvodb-0.1.0.dist-info/METADATA
mvodb-0.1.0.dist-info/RECORD
