Metadata-Version: 2.1
Name: mvodb
Version: 0.1.0
Summary: Rename and move files using metadata from online databases.
Home-page: https://github.com/pawamoy/mvodb
License: ISC
Author: Timothée Mazzucotelli
Author-email: pawamoy@pm.me
Requires-Python: >=3.6,<4.0
Classifier: License :: OSI Approved
Classifier: Programming Language :: Python :: 3
Classifier: Programming Language :: Python :: 3.6
Classifier: Programming Language :: Python :: 3.7
Classifier: Programming Language :: Python :: 3.8
Requires-Dist: guessit (>=3.1.0,<4.0.0)
Requires-Dist: langdetect (>=1.0.7,<2.0.0)
Requires-Dist: tmdbsimple (>=2.2.0,<3.0.0)
Project-URL: Repository, https://github.com/pawamoy/mvodb
